llm_markdownify/__init__.py
llm_markdownify/api.py
llm_markdownify/cache.py
llm_markdownify/cli.py
llm_markdownify/config.py
llm_markdownify/grouping.py
llm_markdownify/llm.py
llm_markdownify/logging.py
llm_markdownify/markdownifier.py
llm_markdownify/pager.py
llm_markdownify/prompt_profiles.py
llm_markdownify/prompts.py
llm_markdownify-0.4.0.dist-info/METADATA
llm_markdownify-0.4.0.dist-info/WHEEL
llm_markdownify-0.4.0.dist-info/entry_points.txt
llm_markdownify-0.4.0.dist-info/licenses/LICENSE
llm_markdownify-0.4.0.dist-info/licenses/NOTICE
llm_markdownify-0.4.0.dist-info/RECORD
