Metadata-Version: 2.4
Name: llm-markdownify
Version: 0.4.0
Summary: Convert PDFs, images to high-quality Markdown using Vision LLMs.
Project-URL: Homepage, https://github.com/sethupavan12/Markdownify
Project-URL: Repository, https://github.com/sethupavan12/Markdownify
Project-URL: Issues, https://github.com/sethupavan12/Markdownify/issues
Author: Sethu Pavan Venkata Reddy Pastula
License: Apache-2.0
License-File: LICENSE
License-File: NOTICE
Keywords: docx,image,jpeg,jpg,litellm,llm,markdown,ocr,pdf,png,vision
Classifier: License :: OSI Approved :: Apache Software License
Classifier: Operating System :: OS Independent
Classifier: Programming Language :: Python :: 3
Classifier: Topic :: Text Processing :: Markup
Classifier: Topic :: Utilities
Requires-Python: >=3.10
Requires-Dist: litellm>=1.43.0
Requires-Dist: pillow>=10.3.0
Requires-Dist: pydantic>=2.7.0
Requires-Dist: pypdfium2>=4.30.0
Requires-Dist: tenacity>=8.2.0
Requires-Dist: tqdm>=4.66.0
Requires-Dist: typer>=0.12.3
Provides-Extra: dev
Requires-Dist: pre-commit>=3.6.0; extra == 'dev'
Requires-Dist: pytest-cov>=5.0.0; extra == 'dev'
Requires-Dist: pytest>=8.2.0; extra == 'dev'
Requires-Dist: ruff>=0.5.6; extra == 'dev'
Provides-Extra: docx
Requires-Dist: docx2pdf>=0.1.8; extra == 'docx'
